wcore_py-0.5.1.dist-info/METADATA
wcore_py-0.5.1.dist-info/WHEEL
wcore_py-0.5.1.dist-info/license_files/LICENSE
wcore_py/__init__.py
wcore_py/wcore_py.cpython-39-darwin.so
wcore_py-0.5.1.dist-info/RECORD
