Metadata-Version: 2.1
Name: wcore_py
Version: 0.5.1
Classifier: Development Status :: 3 - Alpha
Classifier: Programming Language :: Rust
Classifier: Topic :: Education
License-File: LICENSE
Summary: Python bindings for the W programming language
Author-email: James Butcher <jamesbutcher@duck.com>
License: MIT
Project-URL: Source Code, https://github.com/Wlanguage/python-core/
